datapizza/cache/redis/__init__.py
datapizza/cache/redis/cache.py
datapizza_ai_cache_redis-0.0.3.dist-info/METADATA
datapizza_ai_cache_redis-0.0.3.dist-info/WHEEL
datapizza_ai_cache_redis-0.0.3.dist-info/RECORD
