Metadata-Version: 2.4
Name: datapizza-ai-cache-redis
Version: 0.0.3
Summary: An implementation using Redis for datapizza-ai cache
Author-email: Datapizza <datapizza@datapizza.tech>
License: MIT
Classifier: License :: OSI Approved :: MIT License
Classifier: Operating System :: OS Independent
Classifier: Programming Language :: Python :: 3
Requires-Python: <4,>=3.10.0
Requires-Dist: datapizza-ai-core<0.1.0,>=0.0.0
Requires-Dist: redis<6.0.0,>=5.2.1
